{
  "parent": "pebblemod:recipes/root",
  "criteria": {
    "has_red_sandstone_pebble": {
      "trigger": "minecraft:inventory_changed",
      "conditions": {
        "items": [
          {
            "items": "pebblemod:red_sandstone_pebble"
          }
        ]
      }
    },
    "has_the_recipe": {
      "trigger": "minecraft:recipe_unlocked",
      "conditions": {
        "recipe": "pebblemod:red_sandstone_pebbles_to_red_sandstone"
      }
    }
  },
  "requirements": [
    [
      "has_the_recipe",
      "has_red_sandstone_pebble"
    ]
  ],
  "rewards": {
    "recipes": [
      "pebblemod:red_sandstone_pebbles_to_red_sandstone",
      "pebblemod:red_sandstone_to_red_sandstone_pebbles"
    ]
  }
}